hutch15/__init__.py
hutch15/database.py
hutch15/fit_ref.py
hutch15/flu_geometry_routines.py
hutch15/fluorescence.py
hutch15/workspace.py
hutch15/xrays.py
hutch15ID-0.1.1.dist-info/LICENSE
hutch15ID-0.1.1.dist-info/METADATA
hutch15ID-0.1.1.dist-info/WHEEL
hutch15ID-0.1.1.dist-info/top_level.txt
hutch15ID-0.1.1.dist-info/RECORD
