Metadata-Version: 2.1
Name: hutch15ID
Version: 0.1.1
Summary: In this library, you can find anything in the hutch of sector 15ID-C
Home-page: https://github.com/zhul9311/hutch15ID.git
Author: Zhu Liang
Author-email: zliang8@uic.edu
License: MIT License
Keywords: reflectometer,interface,bulk,beam
Platform: any
